kairos_asr/__init__.py
kairos_asr/_version.py
kairos_asr/core/__init__.py
kairos_asr/core/asr.py
kairos_asr/core/cli.py
kairos_asr/core/dtypes.py
kairos_asr/core/feature_extractor.py
kairos_asr/models/__init__.py
kairos_asr/models/decoder.py
kairos_asr/models/encoder.py
kairos_asr/models/onnx_model.py
kairos_asr/models/utils/__init__.py
kairos_asr/models/utils/model_downloader.py
kairos_asr/utils/__init__.py
kairos_asr/utils/audio_utils.py
kairos_asr/utils/device_utils.py
kairos_asr/utils/logger.py
kairos_asr/utils/text_processing.py
kairos_asr/utils/time_utils.py
kairos_asr/utils/vad_utils.py
kairos_asr-0.6.8.dist-info/LICENSE
kairos_asr-0.6.8.dist-info/METADATA
kairos_asr-0.6.8.dist-info/THIRD_PARTY_LICENSES.md
kairos_asr-0.6.8.dist-info/WHEEL
kairos_asr-0.6.8.dist-info/entry_points.txt
kairos_asr-0.6.8.dist-info/top_level.txt
kairos_asr-0.6.8.dist-info/RECORD
