Metadata-Version: 2.1
Name: kairos-asr
Version: 0.6.8
Summary: High-performance Russian speech recognition library based on GigaAM-style RNN-T and ONNX.
Author: Alexey Shimokhin / Alenkar
License: MIT
Project-URL: Homepage, https://github.com/Alenkar/kairos-asr
Project-URL: Repository, https://github.com/Alenkar/kairos-asr
Project-URL: Issues, https://github.com/Alenkar/kairos-asr/issues
Keywords: asr,speech-recognition,russian,onnx,rnnt,gigaam,rnnt-asr
Classifier: License :: OSI Approved :: MIT License
Classifier: Programming Language :: Python :: 3
Classifier: Programming Language :: Python :: 3.10
Classifier: Programming Language :: Python :: 3.11
Classifier: Programming Language :: Python :: 3.12
Classifier: Operating System :: Microsoft :: Windows
Classifier: Operating System :: POSIX :: Linux
Classifier: Intended Audience :: Science/Research
Classifier: Intended Audience :: Developers
Classifier: Topic :: Scientific/Engineering
Classifier: Topic :: Scientific/Engineering :: Artificial Intelligence
Classifier: Topic :: Scientific/Engineering :: Human Machine Interfaces
Classifier: Topic :: Multimedia :: Sound/Audio :: Speech
Classifier: Topic :: Multimedia :: Sound/Audio :: Analysis
Classifier: Topic :: Text Processing :: Linguistic
Classifier: Topic :: Software Development :: Libraries :: Python Modules
Requires-Python: >=3.10
License-File: LICENSE
License-File: docs/THIRD_PARTY_LICENSES.md
Requires-Dist: huggingface-hub>=1.2.3
Requires-Dist: numpy>=1.23.5
Requires-Dist: torch>=2.5.1
Requires-Dist: torchaudio>=2.5.1
Requires-Dist: sentencepiece>=0.2.1
Requires-Dist: scipy>=1.15.3
Provides-Extra: cpu
Requires-Dist: onnxruntime>=1.19.2; extra == "cpu"
Provides-Extra: gpu
Requires-Dist: onnxruntime-gpu>=1.19.2; extra == "gpu"
